CHANGES.txt
CONTRIBUTORS.txt
MANIFEST.in
README.rst
setup.py
docs/LICENSE.MIT
src/koslab/__init__.py
src/koslab.messengerbot.egg-info/PKG-INFO
src/koslab.messengerbot.egg-info/SOURCES.txt
src/koslab.messengerbot.egg-info/dependency_links.txt
src/koslab.messengerbot.egg-info/entry_points.txt
src/koslab.messengerbot.egg-info/namespace_packages.txt
src/koslab.messengerbot.egg-info/not-zip-safe
src/koslab.messengerbot.egg-info/requires.txt
src/koslab.messengerbot.egg-info/top_level.txt
src/koslab/messengerbot/__init__.py
src/koslab/messengerbot/bot.py
src/koslab/messengerbot/bots.py
src/koslab/messengerbot/hub.py
src/koslab/messengerbot/logger.py
src/koslab/messengerbot/request.py
src/koslab/messengerbot/scripts.py
src/koslab/messengerbot/session.py