Metadata-Version: 1.1
Name: koslab.messengerbot
Version: 1.0b3
Summary: Facebook messenger bot framework
Home-page: http://github.com/koslab/koslab.messengerbot/
Author: Izhar Firdaus
Author-email: kagesenshi.87@gmail.com
License: MIT
Keywords: morepath facebook bot messenger chatbot
Platform: UNKNOWN
Classifier: Programming Language :: Python
